<xml version="1.0">
<dashboard>
	<static-widget class="edu.wpi.first.smartdashboard.gui.elements.CameraServerViewer">
		<location x="7" y="38"/>
		<width>332</width>
		<height>201</height>
		<property name="Camera Choice" value=""/>
	</static-widget>
	<widget field="Autonomous Command" type="Command" class="edu.wpi.first.smartdashboard.gui.elements.Command">
		<location x="3" y="3"/>
	</widget>
	<static-widget class="edu.wpi.first.smartdashboard.gui.elements.ConnectionIndicator">
		<location x="18" y="369"/>
		<width>470</width>
		<height>41</height>
	</static-widget>
</dashboard>
<live-window>
</live-window>
	<hidden field="Drive"/>
</xml>